{
  "date": "2025-11-05",
  "area": "tokyo",
  "timezone": "Asia/Tokyo",
  "timescale": "hourly",
  "source": {
    "name": "Estimated (demand + price correlation)",
    "url": "Internal calculation"
  },
  "meta": {
    "avg_renewable_pct": 16.412605922284644,
    "avg_carbon_gco2_kwh": 291.4250795002341,
    "peak_solar_mw": 6038.374044943819,
    "peak_wind_mw": 1041.8999999999999
  },
  "series": [
    {
      "ts": "2025-11-05T00:00:00+09:00",
      "solar_mw": 0,
      "wind_mw": 738.3,
      "hydro_mw": 1968.8,
      "nuclear_mw": 6644.700000000001,
      "lng_mw": 9154.92,
      "coal_mw": 4577.46,
      "other_mw": 1525.8200000000002,
      "total_mw": 24610
    },
    {
      "ts": "2025-11-05T01:00:00+09:00",
      "solar_mw": 0,
      "wind_mw": 706.1999999999999,
      "hydro_mw": 1883.2,
      "nuclear_mw": 6355.8,
      "lng_mw": 8756.88,
      "coal_mw": 4378.44,
      "other_mw": 1459.48,
      "total_mw": 23540
    },
    {
      "ts": "2025-11-05T02:00:00+09:00",
      "solar_mw": 0,
      "wind_mw": 704.1,
      "hydro_mw": 1877.6000000000001,
      "nuclear_mw": 6336.900000000001,
      "lng_mw": 8730.84,
      "coal_mw": 4365.42,
      "other_mw": 1455.14,
      "total_mw": 23470
    },
    {
      "ts": "2025-11-05T03:00:00+09:00",
      "solar_mw": 0,
      "wind_mw": 720.6,
      "hydro_mw": 1921.6000000000001,
      "nuclear_mw": 6485.400000000001,
      "lng_mw": 8935.439999999999,
      "coal_mw": 4467.719999999999,
      "other_mw": 1489.24,
      "total_mw": 24020
    },
    {
      "ts": "2025-11-05T04:00:00+09:00",
      "solar_mw": 0,
      "wind_mw": 737.6999999999999,
      "hydro_mw": 1967.2,
      "nuclear_mw": 6639.3,
      "lng_mw": 9147.48,
      "coal_mw": 4573.74,
      "other_mw": 1524.58,
      "total_mw": 24590
    },
    {
      "ts": "2025-11-05T05:00:00+09:00",
      "solar_mw": 0,
      "wind_mw": 775.5,
      "hydro_mw": 2068,
      "nuclear_mw": 6979.500000000001,
      "lng_mw": 9616.199999999999,
      "coal_mw": 4808.099999999999,
      "other_mw": 1602.7,
      "total_mw": 25850
    },
    {
      "ts": "2025-11-05T06:00:00+09:00",
      "solar_mw": 0,
      "wind_mw": 836.4,
      "hydro_mw": 2230.4,
      "nuclear_mw": 7527.6,
      "lng_mw": 10371.359999999997,
      "coal_mw": 5185.6799999999985,
      "other_mw": 1728.5599999999995,
      "total_mw": 27880
    },
    {
      "ts": "2025-11-05T07:00:00+09:00",
      "solar_mw": 324.97912921348313,
      "wind_mw": 895.8,
      "hydro_mw": 2388.8,
      "nuclear_mw": 8062.200000000001,
      "lng_mw": 10912.93252247191,
      "coal_mw": 5456.466261235955,
      "other_mw": 1818.8220870786517,
      "total_mw": 29860
    },
    {
      "ts": "2025-11-05T08:00:00+09:00",
      "solar_mw": 1436.770617977528,
      "wind_mw": 972.5999999999999,
      "hydro_mw": 2593.6,
      "nuclear_mw": 8753.400000000001,
      "lng_mw": 11198.177629213484,
      "coal_mw": 5599.088814606742,
      "other_mw": 1866.3629382022475,
      "total_mw": 32420
    },
    {
      "ts": "2025-11-05T09:00:00+09:00",
      "solar_mw": 3384.551439606741,
      "wind_mw": 1012.5,
      "hydro_mw": 2700,
      "nuclear_mw": 9112.5,
      "lng_mw": 10524.269136235955,
      "coal_mw": 5262.134568117977,
      "other_mw": 1754.044856039326,
      "total_mw": 33750
    },
    {
      "ts": "2025-11-05T10:00:00+09:00",
      "solar_mw": 6038.374044943819,
      "wind_mw": 1016.0999999999999,
      "hydro_mw": 2709.6,
      "nuclear_mw": 9144.900000000001,
      "lng_mw": 8976.615573033709,
      "coal_mw": 4488.307786516854,
      "other_mw": 1496.1025955056182,
      "total_mw": 33870
    },
    {
      "ts": "2025-11-05T11:00:00+09:00",
      "solar_mw": 5999.4,
      "wind_mw": 999.9,
      "hydro_mw": 2666.4,
      "nuclear_mw": 8999.1,
      "lng_mw": 8799.119999999997,
      "coal_mw": 4399.559999999999,
      "other_mw": 1466.5199999999995,
      "total_mw": 33330
    },
    {
      "ts": "2025-11-05T12:00:00+09:00",
      "solar_mw": 5712.1746067415725,
      "wind_mw": 953.0999999999999,
      "hydro_mw": 2541.6,
      "nuclear_mw": 8577.900000000001,
      "lng_mw": 8391.135235955055,
      "coal_mw": 4195.567617977527,
      "other_mw": 1398.5225393258427,
      "total_mw": 31770
    },
    {
      "ts": "2025-11-05T13:00:00+09:00",
      "solar_mw": 5757.734831460673,
      "wind_mw": 988.5,
      "hydro_mw": 2636,
      "nuclear_mw": 8896.5,
      "lng_mw": 8802.759101123596,
      "coal_mw": 4401.379550561798,
      "other_mw": 1467.126516853933,
      "total_mw": 32950
    },
    {
      "ts": "2025-11-05T14:00:00+09:00",
      "solar_mw": 5819.877303370786,
      "wind_mw": 1004.4,
      "hydro_mw": 2678.4,
      "nuclear_mw": 9039.6,
      "lng_mw": 8962.633617977528,
      "coal_mw": 4481.316808988764,
      "other_mw": 1493.7722696629214,
      "total_mw": 33480
    },
    {
      "ts": "2025-11-05T15:00:00+09:00",
      "solar_mw": 5518.644269662921,
      "wind_mw": 1003.8,
      "hydro_mw": 2676.8,
      "nuclear_mw": 9034.2,
      "lng_mw": 9135.933438202248,
      "coal_mw": 4567.966719101124,
      "other_mw": 1522.6555730337082,
      "total_mw": 33460
    },
    {
      "ts": "2025-11-05T16:00:00+09:00",
      "solar_mw": 1936.4799999999996,
      "wind_mw": 1037.3999999999999,
      "hydro_mw": 2766.4,
      "nuclear_mw": 9336.6,
      "lng_mw": 11701.871999999998,
      "coal_mw": 5850.935999999999,
      "other_mw": 1950.3119999999997,
      "total_mw": 34580
    },
    {
      "ts": "2025-11-05T17:00:00+09:00",
      "solar_mw": 501.4387640449437,
      "wind_mw": 1041.8999999999999,
      "hydro_mw": 2778.4,
      "nuclear_mw": 9377.1,
      "lng_mw": 12618.69674157303,
      "coal_mw": 6309.348370786515,
      "other_mw": 2103.1161235955055,
      "total_mw": 34730
    },
    {
      "ts": "2025-11-05T18:00:00+09:00",
      "solar_mw": 0,
      "wind_mw": 1029.6,
      "hydro_mw": 2745.6,
      "nuclear_mw": 9266.400000000001,
      "lng_mw": 12767.04,
      "coal_mw": 6383.52,
      "other_mw": 2127.84,
      "total_mw": 34320
    },
    {
      "ts": "2025-11-05T19:00:00+09:00",
      "solar_mw": 228.54104494382025,
      "wind_mw": 997.8,
      "hydro_mw": 2660.8,
      "nuclear_mw": 8980.2,
      "lng_mw": 12235.595373033708,
      "coal_mw": 6117.797686516854,
      "other_mw": 2039.2658955056181,
      "total_mw": 33260
    },
    {
      "ts": "2025-11-05T20:00:00+09:00",
      "solar_mw": 216.985702247191,
      "wind_mw": 961.5,
      "hydro_mw": 2564,
      "nuclear_mw": 8653.5,
      "lng_mw": 11792.408578651684,
      "coal_mw": 5896.204289325842,
      "other_mw": 1965.401429775281,
      "total_mw": 32050
    },
    {
      "ts": "2025-11-05T21:00:00+09:00",
      "solar_mw": 239.39807865168538,
      "wind_mw": 911.6999999999999,
      "hydro_mw": 2431.2000000000003,
      "nuclear_mw": 8205.300000000001,
      "lng_mw": 11161.44115280899,
      "coal_mw": 5580.720576404495,
      "other_mw": 1860.2401921348317,
      "total_mw": 30390
    },
    {
      "ts": "2025-11-05T22:00:00+09:00",
      "solar_mw": 0,
      "wind_mw": 862.1999999999999,
      "hydro_mw": 2299.2000000000003,
      "nuclear_mw": 7759.8,
      "lng_mw": 10691.279999999999,
      "coal_mw": 5345.639999999999,
      "other_mw": 1781.88,
      "total_mw": 28740
    },
    {
      "ts": "2025-11-05T23:00:00+09:00",
      "solar_mw": 0,
      "wind_mw": 807.9,
      "hydro_mw": 2154.4,
      "nuclear_mw": 7271.1,
      "lng_mw": 10017.959999999997,
      "coal_mw": 5008.979999999999,
      "other_mw": 1669.6599999999996,
      "total_mw": 26930
    }
  ]
}