{
  "date": "2025-11-23",
  "area": "kansai",
  "timezone": "Asia/Tokyo",
  "timescale": "hourly",
  "source": {
    "name": "Estimated (demand + price correlation)",
    "url": "Internal calculation"
  },
  "meta": {
    "avg_renewable_pct": 16.513365378311036,
    "avg_carbon_gco2_kwh": 290.90616830169813,
    "peak_solar_mw": 2371.5,
    "peak_wind_mw": 440.94
  },
  "series": [
    {
      "ts": "2025-11-23T00:00:00+09:00",
      "solar_mw": 0,
      "wind_mw": 360.84,
      "hydro_mw": 962.24,
      "nuclear_mw": 3247.5600000000004,
      "lng_mw": 4474.415999999999,
      "coal_mw": 2237.2079999999996,
      "other_mw": 745.7359999999999,
      "total_mw": 12028
    },
    {
      "ts": "2025-11-23T01:00:00+09:00",
      "solar_mw": 0,
      "wind_mw": 348.78,
      "hydro_mw": 930.08,
      "nuclear_mw": 3139.02,
      "lng_mw": 4324.871999999999,
      "coal_mw": 2162.4359999999997,
      "other_mw": 720.812,
      "total_mw": 11626
    },
    {
      "ts": "2025-11-23T02:00:00+09:00",
      "solar_mw": 0,
      "wind_mw": 348.9,
      "hydro_mw": 930.4,
      "nuclear_mw": 3140.1000000000004,
      "lng_mw": 4326.36,
      "coal_mw": 2163.18,
      "other_mw": 721.0600000000001,
      "total_mw": 11630
    },
    {
      "ts": "2025-11-23T03:00:00+09:00",
      "solar_mw": 0,
      "wind_mw": 365.58,
      "hydro_mw": 974.88,
      "nuclear_mw": 3290.2200000000003,
      "lng_mw": 4533.191999999999,
      "coal_mw": 2266.5959999999995,
      "other_mw": 755.5319999999999,
      "total_mw": 12186
    },
    {
      "ts": "2025-11-23T04:00:00+09:00",
      "solar_mw": 0,
      "wind_mw": 375.57,
      "hydro_mw": 1001.52,
      "nuclear_mw": 3380.13,
      "lng_mw": 4657.067999999999,
      "coal_mw": 2328.5339999999997,
      "other_mw": 776.1779999999999,
      "total_mw": 12519
    },
    {
      "ts": "2025-11-23T05:00:00+09:00",
      "solar_mw": 0,
      "wind_mw": 374.46,
      "hydro_mw": 998.5600000000001,
      "nuclear_mw": 3370.1400000000003,
      "lng_mw": 4643.304,
      "coal_mw": 2321.652,
      "other_mw": 773.8840000000001,
      "total_mw": 12482
    },
    {
      "ts": "2025-11-23T06:00:00+09:00",
      "solar_mw": 0,
      "wind_mw": 374.25,
      "hydro_mw": 998,
      "nuclear_mw": 3368.25,
      "lng_mw": 4640.7,
      "coal_mw": 2320.35,
      "other_mw": 773.45,
      "total_mw": 12475
    },
    {
      "ts": "2025-11-23T07:00:00+09:00",
      "solar_mw": 106.82148682140048,
      "wind_mw": 376.59,
      "hydro_mw": 1004.24,
      "nuclear_mw": 3389.3100000000004,
      "lng_mw": 4605.62310790716,
      "coal_mw": 2302.81155395358,
      "other_mw": 767.6038513178601,
      "total_mw": 12553
    },
    {
      "ts": "2025-11-23T08:00:00+09:00",
      "solar_mw": 483.9212726199842,
      "wind_mw": 380.55,
      "hydro_mw": 1014.8000000000001,
      "nuclear_mw": 3424.9500000000003,
      "lng_mw": 4428.4672364280095,
      "coal_mw": 2214.2336182140048,
      "other_mw": 738.0778727380016,
      "total_mw": 12685
    },
    {
      "ts": "2025-11-23T09:00:00+09:00",
      "solar_mw": 1268.4845676632574,
      "wind_mw": 384.84,
      "hydro_mw": 1026.24,
      "nuclear_mw": 3463.5600000000004,
      "lng_mw": 4010.925259402045,
      "coal_mw": 2005.4626297010225,
      "other_mw": 668.4875432336743,
      "total_mw": 12828
    },
    {
      "ts": "2025-11-23T10:00:00+09:00",
      "solar_mw": 2332.62,
      "wind_mw": 388.77,
      "hydro_mw": 1036.72,
      "nuclear_mw": 3498.9300000000003,
      "lng_mw": 3421.176,
      "coal_mw": 1710.588,
      "other_mw": 570.196,
      "total_mw": 12959
    },
    {
      "ts": "2025-11-23T11:00:00+09:00",
      "solar_mw": 2371.5,
      "wind_mw": 395.25,
      "hydro_mw": 1054,
      "nuclear_mw": 3557.2500000000005,
      "lng_mw": 3478.2,
      "coal_mw": 1739.1,
      "other_mw": 579.7,
      "total_mw": 13175
    },
    {
      "ts": "2025-11-23T12:00:00+09:00",
      "solar_mw": 2362.3199999999997,
      "wind_mw": 393.71999999999997,
      "hydro_mw": 1049.92,
      "nuclear_mw": 3543.48,
      "lng_mw": 3464.7360000000003,
      "coal_mw": 1732.3680000000002,
      "other_mw": 577.456,
      "total_mw": 13124
    },
    {
      "ts": "2025-11-23T13:00:00+09:00",
      "solar_mw": 2269.08,
      "wind_mw": 378.18,
      "hydro_mw": 1008.48,
      "nuclear_mw": 3403.6200000000003,
      "lng_mw": 3327.9839999999995,
      "coal_mw": 1663.9919999999997,
      "other_mw": 554.664,
      "total_mw": 12606
    },
    {
      "ts": "2025-11-23T14:00:00+09:00",
      "solar_mw": 2225.16,
      "wind_mw": 370.86,
      "hydro_mw": 988.96,
      "nuclear_mw": 3337.7400000000002,
      "lng_mw": 3263.568,
      "coal_mw": 1631.784,
      "other_mw": 543.9280000000001,
      "total_mw": 12362
    },
    {
      "ts": "2025-11-23T15:00:00+09:00",
      "solar_mw": 2209.7437293469707,
      "wind_mw": 372.59999999999997,
      "hydro_mw": 993.6,
      "nuclear_mw": 3353.4,
      "lng_mw": 3294.3937623918177,
      "coal_mw": 1647.1968811959089,
      "other_mw": 549.0656270653029,
      "total_mw": 12420
    },
    {
      "ts": "2025-11-23T16:00:00+09:00",
      "solar_mw": 837.6327112509834,
      "wind_mw": 381.57,
      "hydro_mw": 1017.52,
      "nuclear_mw": 3434.13,
      "lng_mw": 4228.88837324941,
      "coal_mw": 2114.444186624705,
      "other_mw": 704.8147288749017,
      "total_mw": 12719
    },
    {
      "ts": "2025-11-23T17:00:00+09:00",
      "solar_mw": 198.30591188040913,
      "wind_mw": 410.01,
      "hydro_mw": 1093.3600000000001,
      "nuclear_mw": 3690.09,
      "lng_mw": 4965.140452871754,
      "coal_mw": 2482.570226435877,
      "other_mw": 827.5234088119591,
      "total_mw": 13667
    },
    {
      "ts": "2025-11-23T18:00:00+09:00",
      "solar_mw": 0,
      "wind_mw": 440.94,
      "hydro_mw": 1175.84,
      "nuclear_mw": 3968.46,
      "lng_mw": 5467.656,
      "coal_mw": 2733.828,
      "other_mw": 911.2760000000001,
      "total_mw": 14698
    },
    {
      "ts": "2025-11-23T19:00:00+09:00",
      "solar_mw": 91.67007922895358,
      "wind_mw": 436.22999999999996,
      "hydro_mw": 1163.28,
      "nuclear_mw": 3926.07,
      "lng_mw": 5354.249952462627,
      "coal_mw": 2677.1249762313137,
      "other_mw": 892.3749920771047,
      "total_mw": 14541
    },
    {
      "ts": "2025-11-23T20:00:00+09:00",
      "solar_mw": 94.23118961447679,
      "wind_mw": 433.8,
      "hydro_mw": 1156.8,
      "nuclear_mw": 3904.2000000000003,
      "lng_mw": 5322.581286231314,
      "coal_mw": 2661.290643115657,
      "other_mw": 887.0968810385525,
      "total_mw": 14460
    },
    {
      "ts": "2025-11-23T21:00:00+09:00",
      "solar_mw": 92.16940078678206,
      "wind_mw": 421.56,
      "hydro_mw": 1124.16,
      "nuclear_mw": 3794.0400000000004,
      "lng_mw": 5172.04235952793,
      "coal_mw": 2586.021179763965,
      "other_mw": 862.0070599213218,
      "total_mw": 14052
    },
    {
      "ts": "2025-11-23T22:00:00+09:00",
      "solar_mw": 0,
      "wind_mw": 398.31,
      "hydro_mw": 1062.16,
      "nuclear_mw": 3584.7900000000004,
      "lng_mw": 4939.044,
      "coal_mw": 2469.522,
      "other_mw": 823.174,
      "total_mw": 13277
    },
    {
      "ts": "2025-11-23T23:00:00+09:00",
      "solar_mw": 0,
      "wind_mw": 378.71999999999997,
      "hydro_mw": 1009.9200000000001,
      "nuclear_mw": 3408.48,
      "lng_mw": 4696.128000000001,
      "coal_mw": 2348.0640000000003,
      "other_mw": 782.6880000000001,
      "total_mw": 12624
    }
  ]
}